lsoc/__init__.py
lsoc/lsoc.py
lsoc-0.1.4.dist-info/LICENSE.txt
lsoc-0.1.4.dist-info/METADATA
lsoc-0.1.4.dist-info/WHEEL
lsoc-0.1.4.dist-info/entry_points.txt
lsoc-0.1.4.dist-info/top_level.txt
lsoc-0.1.4.dist-info/RECORD
